{
  "apkLink":"",
  "audit":1,
  "author":"",
  "chapterId":494,
  "chapterName":"广场",
  "collect":false,
  "courseId":13,
  "desc":"",
  "envelopePic":"",
  "fresh":true,
  "id":9811,
  "link":"https://blog.csdn.net/u010055819/article/details/102600127",
  "niceDate":"25分钟前",
  "niceShareDate":"25分钟前",
  "origin":"",
  "prefix":"",
  "projectLink":"",
  "publishTime":1571367352000,
  "selfVisible":0,
  "shareDate":1571367352000,
  "shareUser":"lifeidroid",
  "superChapterId":494,
  "superChapterName":"广场Tab",

  "title":"【<em class='highlight'>Flutter</em>学习轨迹】第四章：不破不立，永不放弃",
  "type":0,
  "userId":31643,
  "visible":0,
  "zan":0
}